{"url": "http://www.xwfwm.co/robin-wright-ana-de-armas-and-sylvia-hoeks-help-blade-runner-2049-join-the-gender-revolution/", "text": "Robin Wright, Ana de Armas and Sylvia Hoeks Help Blade\n\nRobin Wright, Ana de Armas and Sylvia Hoeks keep up with Ryan Gosling. Robin Wright, Ana de Armas and Sylvia Hoeks Help Blade Runner 2049 Join the Gender Revolution \u2026\n\nBlade Runner 2049 \u2013 Wikipedia\n\nBlade Runner 2049 is a 2017 American neo-noir science fiction film directed by Denis Villeneuve and written by Hampton Fancher and Michael Green. A sequel to the 1982 film Blade Runner , the film stars Ryan Gosling and Harrison Ford , with Ana de Armas , Sylvia Hoeks , Robin Wright , Mackenzie Davis , Carla Juri , Lennie James , Dave Bautista , \u2026\n\nDirected by: Denis Villeneuve\n\nVideoETA: Blade Runner 2049 Ryan Gosling,Harrison Ford,Ana\n\nThirty years after the events of the first film, a new blade runner, LAPD Officer K (Ryan Gosling), unearths a long-buried secret that has the potential to plunge what\u2019s left of society into chaos. K\u2019s discovery leads him on a quest to find Rick Deckard (Harrison Ford), a former LAPD blade runner who has been missing for 30 years.\n\nShould I Watch..? Blade Runner 2049 | HubPages\n\nBlade Runner 2049 is a science fiction film released in 2017 and is a sequel to the highly regarded 1982 film Blade Runner. Directed by Denis Villeneuve, the film is a continuation of the story set thirty years after the events of the first film.\n\nJared Leto is shown for first time in Blade Runner 2049\n\ncast: The sci-fi film also stars Ana de Armas, Sylvia Hoeks, Carla Juri, Barkhad Abdi, and Dave Bautista Number one: Blade Runner 2049 is the sequel to the classic Blade Runner where Ford starred as cyborg chasing cop, Rick Deckard.\n\nBlade Runner 2049 [2017] [R] \u2013 7.7.5 | Parent Rating\n\nOne Blade Runner (Ryan Gosling) uncovers a mystery that leads him to search for a former Blade Runner (Harrison Ford) who\u2019s been missing for three decades. Also with Dave Bautista, Robin Wright, Jared Leto, Ana de Armas, Sylvia Hoeks, Carla Juri and Mackenzie Davis. Directed by Denis Villeneuve.\n\nThe girls of \u2018Blade Runner 2049\u2019 Sylvia Hoeks, Ana de\n\nOct 05, 2017 \u00b7 The girls of \u2018Blade Runner 2049\u2019 Sylvia Hoeks, Ana de Armas & Mackenzie Davis Blade Runner 2049 | Ana De Armas & Sylvia Hoeks GUESS THE GADGET challenge Sylvia Hoeks, Ana de Armas,\n\nReview: Blade Runner 2049 \u2013 Geeks Under Grace\n\nAna de Armas, Blade Runner 2049 Christian Movie review, Blade Runner 2049 Movie Review, Christian, Denis Villeneuve, harrison ford, Jared Leto, review, Robin Wright, Ryan Gosling, Sylvia Hoeks About the Author\n\nHarrison Ford warns Ryan Gosling in Blade Runner \u2026\n\nWarner Bros. dropped a new trailer for Blade Runner 2049, giving a better glimpse of what\u2019s in store for the highly-anticipated sequel. (center) poses with co-stars Ana de Armas (left), and\n\n\u2018Blade Runner 2049\u2019 Running Time \u2014 Two Hours, 32 \u2026\n\nHarrison Ford, Ryan Gosling, Jared Leto, Robin Wright, Ana de Armas, Sylvia Hoeks, Carla Juri, Barkhad Abdi, and Dave Bautista are \u2026", "images": [], "top_img": "", "keywords": [], "authors": [], "canonical_link": "http://www.xwfwm.co/robin-wright-ana-de-armas-and-sylvia-hoeks-help-blade-runner-2049-join-the-gender-revolution/", "title": "Robin Wright, Ana de Armas and Sylvia Hoeks Help Blade Runner 2049 Join the Gender Revolution \u2013 XWF", "meta_data": {"viewport": "width=device-width, initial-scale=1"}, "movies": [], "publish_date": null, "source": "http://www.xwfwm.co", "summary": ""}