{"url": "https://bckonline.com/2018/04/27/tia-mowry-takes-us-inside-her-daughters-nursery/", "text": "Tia Mowry is giving us an inside look at her baby girl\u2019s room in her latest \u201cQuick Fix\u201d segment. The celebrity mom shows us everything from shoes she has purchased for her daughter to the decor, which is nothing short of bright and beautiful.\n\nTia Mowry\u2019s Baby Girl Nursery Reveal An organic color palette & minimal clutter make for an ultra calming environment, which is perfect for me & baby girl!Take a peek inside her nursery that I created with my dear friend Jake Alexander. See more of his work here: http://bit.ly/JakeAlexanderQFMake sure to follow Quick Fix for more episodes. Posted by Tia Mowry's Quick Fix on Friday, April 27, 2018\n\n\u201cYou asked and you got it,\u201d Tia told her Instagram fans on Friday. \u201cBaby girl is almost here and we are READY,\u201d she exclaimed. \u201cI\u2019m loving the earth tones and calm vibes of all the decor, and can\u2019t wait to see her grow into this gorgeous room.\u201d\n\nJake Alexander was one of the masterminds behind Tia\u2019s nursery creation. The interior designer did a spectacular job of putting together an airy space in which the newest member of the Hardrict family can thrive. \u201cAn organic color palette & minimal clutter make for an ultra calming environment, which is perfect for me and baby girl,\u201d Tia shared with her Facebook subscribers.\n\nWe are waiting with great anticipation for the arrival of Tia and her husband Cory Hardrict\u2019s baby girl. It was just a few weeks ago that the expectant actress shared gratitude over her family\u2019s expansion. \u201cI was in denial, to be honest with you,\u201d Tia said during an interview with Mini magazine. \u201cI probably went through 20 pregnancy tests. It was hard for me to get pregnant, so I wanted to be super positive before I got too excited,\u201d she explained.\n\nBoth Tia and her husband were overjoyed to learn that they were expecting a girl. \u201cI started crying because I knew how much my husband wanted to have a girl,\u201d the celebrity mom told media.\n\nThe Hardict\u2019s baby girl will join their son, Cree Hardrict, at home in coming weeks. Stay tuned for more celebrity pregnancy news!", "images": ["https://bckonline.com/wp-content/uploads/2019/07/mariahcarey-120x86.jpg", "https://bckonline.com/wp-content/uploads/2018/04/Neyo-75x75.jpg", "https://bckonline.com/wp-content/uploads/2016/10/logo.png", "https://bckonline.com/wp-content/uploads/2019/06/yungmiami-1-350x250.jpg", "https://bckonline.com/wp-content/uploads/2019/07/kawhileonardfamily-120x86.jpg", "https://bckonline.com/wp-content/uploads/2019/07/kardashian-kids-120x86.jpg", "https://bckonline.com/wp-content/uploads/2019/07/union-120x86.jpg", "https://bckonline.com/wp-content/uploads/2018/04/Mowry-3.jpg", "https://bckonline.com/wp-content/uploads/2016/09/Sarie-150x150.png", "https://bckonline.com/wp-content/uploads/2019/07/brookevalentine-350x350.jpg", "https://bckonline.com/wp-content/uploads/2019/07/mariahcarey-350x350.jpg", "https://bckonline.com/wp-content/uploads/2019/06/cole-350x250.jpg", "https://bckonline.com/wp-content/uploads/2019/07/brookevalentine-350x250.jpg", "https://bckonline.com/wp-content/uploads/2019/06/Kimbella-350x250.jpg", "https://bckonline.com/wp-content/uploads/2019/07/CIARARUSSELL-120x86.jpg", "https://bckonline.com/wp-content/uploads/2019/07/kardashian-kids-350x350.jpg", "https://bckonline.com/wp-content/uploads/2019/07/union-350x350.jpg", "https://bckonline.com/wp-content/uploads/2018/04/Mowry1.jpg", "https://bckonline.com/wp-content/uploads/2019/07/brookevalentine-120x86.jpg", "https://bckonline.com/wp-content/uploads/2019/06/evamarcille3-120x86.jpg", "https://bckonline.com/wp-content/uploads/2019/06/Kimbella-120x86.jpg", "https://bckonline.com/wp-content/uploads/2019/06/evamarcille3-350x250.jpg"], "top_img": "https://bckonline.com/wp-content/uploads/2018/04/Mowry-3.jpg", "keywords": [], "authors": ["Sarie Is A Writer", "Editor For Bck'S Los Angeles Division. She Also Shares Stories On Medium That Are Meant To Encourage Thought", "Discussion. You Can", "Cash", "Her", "Ousside", "Enjoying Nature", "Classical Literature. Pop Culture Is Pretty Fun", "Too"], "canonical_link": "https://bckonline.com/2018/04/27/tia-mowry-takes-us-inside-her-daughters-nursery/", "title": "TIA MOWRY TAKES US INSIDE HER DAUGHTER\u2019S NURSERY", "meta_data": {"viewport": "width=device-width, initial-scale=1, user-scalable=yes", "og": {"type": "article", "title": "TIA MOWRY TAKES US INSIDE HER DAUGHTER'S NURSERY", "site_name": "BCK Online", "description": "Tia Mowry is giving us an inside look at her baby girl's room in her latest \"Quick Fix\" segment. The celebrity mom shows us everything from shoes she has", "url": "https://bckonline.com/2018/04/27/tia-mowry-takes-us-inside-her-daughters-nursery/", "locale": "en_US", "image": {"identifier": "https://bckonline.com/wp-content/uploads/2018/04/Mowry-3.jpg", "secure_url": "https://bckonline.com/wp-content/uploads/2018/04/Mowry-3.jpg", "width": 640, "height": 610}, "updated_time": "2018-04-29T23:47:49+00:00"}, "article": {"published_time": "2018-04-27T15:35:39+00:00", "modified_time": "2018-04-29T23:47:49+00:00", "section": "Bump Watch", "tag": "Tia Mowry pregnant"}, "twitter": {"card": "summary_large_image", "title": "TIA MOWRY TAKES US INSIDE HER DAUGHTER\u2019S NURSERY", "description": "Tia Mowry is giving us an inside look at her baby girl's room in her latest \"Quick Fix\" segment. The", "url": "https://bckonline.com/2018/04/27/tia-mowry-takes-us-inside-her-daughters-nursery/", "image": {"src": "https://bckonline.com/wp-content/uploads/2018/04/Mowry-3.jpg", "width": 640, "height": 610}}, "description": "Tia Mowry is giving us an inside look at her baby girl's room in her latest \"Quick Fix\" segment. The celebrity mom shows us everything from shoes she has", "generator": "Powered by WPBakery Page Builder - drag and drop page builder for WordPress.", "onesignal": "wordpress-plugin", "msapplication-TileImage": "https://bckonline.com/wp-content/uploads/2016/09/cropped-BCK-Video-Logo-COLOR-270x270.png"}, "movies": [], "publish_date": 1524801600.0, "source": "https://bckonline.com", "summary": ""}